fastapi_basekit/__init__.py
fastapi_basekit/aio/__init__.py
fastapi_basekit/aio/beanie/__init__.py
fastapi_basekit/aio/beanie/controller/__init__.py
fastapi_basekit/aio/beanie/controller/base.py
fastapi_basekit/aio/beanie/repository/__init__.py
fastapi_basekit/aio/beanie/repository/base.py
fastapi_basekit/aio/beanie/service/__init__.py
fastapi_basekit/aio/beanie/service/base.py
fastapi_basekit/aio/controller/__init__.py
fastapi_basekit/aio/controller/base.py
fastapi_basekit/aio/permissions/__init__.py
fastapi_basekit/aio/permissions/base.py
fastapi_basekit/aio/sqlalchemy/__init__.py
fastapi_basekit/aio/sqlalchemy/controller/__init__.py
fastapi_basekit/aio/sqlalchemy/controller/base.py
fastapi_basekit/aio/sqlalchemy/repository/__init__.py
fastapi_basekit/aio/sqlalchemy/repository/base.py
fastapi_basekit/aio/sqlalchemy/service/__init__.py
fastapi_basekit/aio/sqlalchemy/service/base.py
fastapi_basekit/exceptions/__init__.py
fastapi_basekit/exceptions/api_exceptions.py
fastapi_basekit/exceptions/handler.py
fastapi_basekit/schema/__init__.py
fastapi_basekit/schema/base.py
fastapi_basekit/schema/jwt.py
fastapi_basekit/schema/schema.py
fastapi_basekit/servicios/__init__.py
fastapi_basekit/servicios/thrid/__init__.py
fastapi_basekit/servicios/thrid/jwt.py
fastapi_basekit-0.1.23.dist-info/LICENSE
fastapi_basekit-0.1.23.dist-info/METADATA
fastapi_basekit-0.1.23.dist-info/WHEEL
fastapi_basekit-0.1.23.dist-info/top_level.txt
fastapi_basekit-0.1.23.dist-info/RECORD
