Metadata-Version: 2.1
Name: fastapi-basekit
Version: 0.1.23
Summary: Utilities and base classes for FastAPI async projects (Beanie or SQLAlchemy)
Author-email: Jerson Moreno <jerson.ml820@hotmail.com>
License: MIT
Project-URL: Homepage, https://github.com/mundobien2025/fastapi-basekit
Project-URL: Repository, https://github.com/mundobien2025/fastapi-basekit
Project-URL: Issues, https://github.com/mundobien2025/fastapi-basekit/issues
Classifier: Development Status :: 5 - Production/Stable
Classifier: Programming Language :: Python :: 3
Classifier: Framework :: FastAPI
Classifier: License :: OSI Approved :: MIT License
Classifier: Operating System :: OS Independent
Requires-Python: >=3.11
License-File: LICENSE
Requires-Dist: fastapi >=0.116.1
Requires-Dist: pydantic <3,>=2.11.7
Requires-Dist: fastapi-restful[all] >=0.6.0
Provides-Extra: all
Requires-Dist: beanie >=1.24.0 ; extra == 'all'
Requires-Dist: motor >=3.3.0 ; extra == 'all'
Requires-Dist: SQLAlchemy[asyncio] >=2.0.0 ; extra == 'all'
Requires-Dist: psycopg2 >=2.9.0 ; extra == 'all'
Provides-Extra: beanie
Requires-Dist: beanie >=1.24.0 ; extra == 'beanie'
Requires-Dist: motor >=3.3.0 ; extra == 'beanie'
Provides-Extra: sqlalchemy
Requires-Dist: SQLAlchemy[asyncio] >=2.0.0 ; extra == 'sqlalchemy'
Requires-Dist: psycopg2 >=2.9.0 ; extra == 'sqlalchemy'
